{"2023-08-08T03:00:00.000+00:00":[{"routeShortName":"326","totalEntries":4539,"totalTrips":49,"collectedTrips":62,"matchedTrips":45,"percentageMatched":0.9183673469387755},{"routeShortName":"9211","totalEntries":10437,"totalTrips":103,"collectedTrips":148,"matchedTrips":68,"percentageMatched":0.6601941747572816},{"routeShortName":"9106","totalEntries":6097,"totalTrips":97,"collectedTrips":128,"matchedTrips":53,"percentageMatched":0.5463917525773195},{"routeShortName":"SC03A","totalEntries":2477,"totalTrips":26,"collectedTrips":32,"matchedTrips":20,"percentageMatched":0.7692307692307693},{"routeShortName":"4205","totalEntries":6315,"totalTrips":100,"collectedTrips":133,"matchedTrips":52,"percentageMatched":0.52},{"routeShortName":"4403A","totalEntries":19926,"totalTrips":88,"collectedTrips":139,"matchedTrips":75,"percentageMatched":0.8522727272727273},{"routeShortName":"9408","totalEntries":8643,"totalTrips":109,"collectedTrips":135,"matchedTrips":81,"percentageMatched":0.7431192660550459},{"routeShortName":"8205","totalEntries":9703,"totalTrips":102,"collectedTrips":147,"matchedTrips":59,"percentageMatched":0.5784313725490197},{"routeShortName":"712","totalEntries":6686,"totalTrips":71,"collectedTrips":87,"matchedTrips":68,"percentageMatched":0.9577464788732394},{"routeShortName":"4108","totalEntries":21005,"totalTrips":112,"collectedTrips":171,"matchedTrips":105,"percentageMatched":0.9375},{"routeShortName":"627","totalEntries":9014,"totalTrips":120,"collectedTrips":161,"matchedTrips":103,"percentageMatched":0.8583333333333333},{"routeShortName":"608","totalEntries":12220,"totalTrips":57,"collectedTrips":87,"matchedTrips":48,"percentageMatched":0.8421052631578947},{"routeShortName":"808","totalEntries":6117,"totalTrips":74,"collectedTrips":99,"matchedTrips":47,"percentageMatched":0.6351351351351351},{"routeShortName":"309","totalEntries":6618,"totalTrips":68,"collectedTrips":81,"matchedTrips":60,"percentageMatched":0.8823529411764706},{"routeShortName":"328","totalEntries":7321,"totalTrips":59,"collectedTrips":78,"matchedTrips":52,"percentageMatched":0.8813559322033898},{"routeShortName":"3302D","totalEntries":8041,"totalTrips":49,"collectedTrips":82,"matchedTrips":33,"percentageMatched":0.673469387755102},{"routeShortName":"341","totalEntries":10615,"totalTrips":53,"collectedTrips":75,"matchedTrips":47,"percentageMatched":0.8867924528301887},{"routeShortName":"5250","totalEntries":20548,"totalTrips":243,"collectedTrips":377,"matchedTrips":146,"percentageMatched":0.6008230452674898},{"routeShortName":"33","totalEntries":28632,"totalTrips":124,"collectedTrips":1172,"matchedTrips":121,"percentageMatched":0.9758064516129032},{"routeShortName":"8101","totalEntries":9455,"totalTrips":132,"collectedTrips":215,"matchedTrips":88,"percentageMatched":0.6666666666666666},{"routeShortName":"9250","totalEntries":20616,"totalTrips":160,"collectedTrips":313,"matchedTrips":97,"percentageMatched":0.60625},{"routeShortName":"637","totalEntries":4970,"totalTrips":48,"collectedTrips":61,"matchedTrips":47,"percentageMatched":0.9791666666666666},{"routeShortName":"338","totalEntries":1821,"totalTrips":15,"collectedTrips":23,"matchedTrips":14,"percentageMatched":0.9333333333333333},{"routeShortName":"615","totalEntries":11798,"totalTrips":107,"collectedTrips":149,"matchedTrips":103,"percentageMatched":0.9626168224299065},{"routeShortName":"738","totalEntries":8898,"totalTrips":69,"collectedTrips":107,"matchedTrips":60,"percentageMatched":0.8695652173913043},{"routeShortName":"401","totalEntries":341,"totalTrips":32,"collectedTrips":38,"matchedTrips":5,"percentageMatched":0.15625},{"routeShortName":"823","totalEntries":4700,"totalTrips":62,"collectedTrips":96,"matchedTrips":42,"percentageMatched":0.6774193548387096},{"routeShortName":"1502","totalEntries":18051,"totalTrips":182,"collectedTrips":256,"matchedTrips":108,"percentageMatched":0.5934065934065934},{"routeShortName":"319","totalEntries":76,"totalTrips":38,"collectedTrips":34,"matchedTrips":1,"percentageMatched":0.02631578947368421},{"routeShortName":"85","totalEntries":9141,"totalTrips":57,"collectedTrips":282,"matchedTrips":55,"percentageMatched":0.9649122807017544},{"routeShortName":"3053","totalEntries":11122,"totalTrips":67,"collectedTrips":97,"matchedTrips":61,"percentageMatched":0.9104477611940298},{"routeShortName":"1509","totalEntries":15027,"totalTrips":129,"collectedTrips":193,"matchedTrips":85,"percentageMatched":0.6589147286821705},{"routeShortName":"719","totalEntries":11775,"totalTrips":92,"collectedTrips":142,"matchedTrips":86,"percentageMatched":0.9347826086956522},{"routeShortName":"716","totalEntries":4131,"totalTrips":50,"collectedTrips":63,"matchedTrips":47,"percentageMatched":0.94},{"routeShortName":"105","totalEntries":1333,"totalTrips":35,"collectedTrips":41,"matchedTrips":22,"percentageMatched":0.6285714285714286},{"routeShortName":"625","totalEntries":3893,"totalTrips":52,"collectedTrips":65,"matchedTrips":49,"percentageMatched":0.9423076923076923},{"routeShortName":"203","totalEntries":4092,"totalTrips":32,"collectedTrips":177,"matchedTrips":30,"percentageMatched":0.9375},{"routeShortName":"644","totalEntries":7088,"totalTrips":70,"collectedTrips":84,"matchedTrips":62,"percentageMatched":0.8857142857142857},{"routeShortName":"634","totalEntries":14192,"totalTrips":110,"collectedTrips":140,"matchedTrips":104,"percentageMatched":0.9454545454545454},{"routeShortName":"5107","totalEntries":9586,"totalTrips":77,"collectedTrips":145,"matchedTrips":58,"percentageMatched":0.7532467532467533},{"routeShortName":"8107","totalEntries":6101,"totalTrips":96,"collectedTrips":116,"matchedTrips":65,"percentageMatched":0.6770833333333334},{"routeShortName":"718","totalEntries":4336,"totalTrips":45,"collectedTrips":57,"matchedTrips":42,"percentageMatched":0.9333333333333333},{"routeShortName":"SC02A","totalEntries":5422,"totalTrips":66,"collectedTrips":83,"matchedTrips":46,"percentageMatched":0.696969696969697},{"routeShortName":"3501A","totalEntries":7746,"totalTrips":111,"collectedTrips":141,"matchedTrips":57,"percentageMatched":0.5135135135135135},{"routeShortName":"402","totalEntries":748,"totalTrips":31,"collectedTrips":23,"matchedTrips":15,"percentageMatched":0.4838709677419355},{"routeShortName":"2151","totalEntries":11672,"totalTrips":131,"collectedTrips":196,"matchedTrips":84,"percentageMatched":0.6412213740458015},{"routeShortName":"9502","totalEntries":8117,"totalTrips":88,"collectedTrips":134,"matchedTrips":56,"percentageMatched":0.6363636363636364},{"routeShortName":"202","totalEntries":4798,"totalTrips":54,"collectedTrips":71,"matchedTrips":45,"percentageMatched":0.8333333333333334},{"routeShortName":"619","totalEntries":7979,"totalTrips":81,"collectedTrips":101,"matchedTrips":75,"percentageMatched":0.9259259259259259},{"routeShortName":"103","totalEntries":5604,"totalTrips":64,"collectedTrips":99,"matchedTrips":47,"percentageMatched":0.734375},{"routeShortName":"5502C","totalEntries":12562,"totalTrips":71,"collectedTrips":106,"matchedTrips":57,"percentageMatched":0.8028169014084507},{"routeShortName":"717","totalEntries":5122,"totalTrips":48,"collectedTrips":68,"matchedTrips":44,"percentageMatched":0.9166666666666666},{"routeShortName":"2034","totalEntries":5901,"totalTrips":43,"collectedTrips":62,"matchedTrips":34,"percentageMatched":0.7906976744186046},{"routeShortName":"2102","totalEntries":6058,"totalTrips":103,"collectedTrips":131,"matchedTrips":63,"percentageMatched":0.6116504854368932},{"routeShortName":"506","totalEntries":4510,"totalTrips":40,"collectedTrips":57,"matchedTrips":31,"percentageMatched":0.775},{"routeShortName":"9550","totalEntries":4032,"totalTrips":90,"collectedTrips":128,"matchedTrips":33,"percentageMatched":0.36666666666666664},{"routeShortName":"4111","totalEntries":13468,"totalTrips":143,"collectedTrips":207,"matchedTrips":88,"percentageMatched":0.6153846153846154},{"routeShortName":"815","totalEntries":20460,"totalTrips":135,"collectedTrips":407,"matchedTrips":109,"percentageMatched":0.8074074074074075},{"routeShortName":"9501","totalEntries":6760,"totalTrips":89,"collectedTrips":123,"matchedTrips":59,"percentageMatched":0.6629213483146067},{"routeShortName":"315","totalEntries":2082,"totalTrips":43,"collectedTrips":44,"matchedTrips":35,"percentageMatched":0.813953488372093},{"routeShortName":"305","totalEntries":15054,"totalTrips":83,"collectedTrips":1060,"matchedTrips":82,"percentageMatched":0.9879518072289156},{"routeShortName":"4032","totalEntries":10293,"totalTrips":60,"collectedTrips":85,"matchedTrips":52,"percentageMatched":0.8666666666666667},{"routeShortName":"4037","totalEntries":8524,"totalTrips":54,"collectedTrips":76,"matchedTrips":44,"percentageMatched":0.8148148148148148},{"routeShortName":"510","totalEntries":10450,"totalTrips":67,"collectedTrips":653,"matchedTrips":66,"percentageMatched":0.9850746268656716},{"routeShortName":"SC01A","totalEntries":7635,"totalTrips":60,"collectedTrips":80,"matchedTrips":59,"percentageMatched":0.9833333333333333},{"routeShortName":"3029","totalEntries":13783,"totalTrips":57,"collectedTrips":92,"matchedTrips":43,"percentageMatched":0.7543859649122807},{"routeShortName":"64","totalEntries":28003,"totalTrips":128,"collectedTrips":637,"matchedTrips":113,"percentageMatched":0.8828125},{"routeShortName":"614","totalEntries":12766,"totalTrips":158,"collectedTrips":218,"matchedTrips":121,"percentageMatched":0.7658227848101266},{"routeShortName":"8203","totalEntries":6770,"totalTrips":101,"collectedTrips":154,"matchedTrips":44,"percentageMatched":0.43564356435643564},{"routeShortName":"633","totalEntries":4655,"totalTrips":55,"collectedTrips":69,"matchedTrips":50,"percentageMatched":0.9090909090909091},{"routeShortName":"8106","totalEntries":6715,"totalTrips":89,"collectedTrips":119,"matchedTrips":43,"percentageMatched":0.48314606741573035},{"routeShortName":"3051","totalEntries":22153,"totalTrips":78,"collectedTrips":136,"matchedTrips":74,"percentageMatched":0.9487179487179487},{"routeShortName":"68","totalEntries":7076,"totalTrips":63,"collectedTrips":85,"matchedTrips":52,"percentageMatched":0.8253968253968254},{"routeShortName":"643","totalEntries":4770,"totalTrips":50,"collectedTrips":61,"matchedTrips":48,"percentageMatched":0.96},{"routeShortName":"9104","totalEntries":8232,"totalTrips":114,"collectedTrips":158,"matchedTrips":66,"percentageMatched":0.5789473684210527},{"routeShortName":"342","totalEntries":10493,"totalTrips":83,"collectedTrips":134,"matchedTrips":65,"percentageMatched":0.7831325301204819},{"routeShortName":"9201","totalEntries":6748,"totalTrips":86,"collectedTrips":117,"matchedTrips":52,"percentageMatched":0.6046511627906976},{"routeShortName":"9205","totalEntries":11367,"totalTrips":161,"collectedTrips":228,"matchedTrips":84,"percentageMatched":0.5217391304347826},{"routeShortName":"5201","totalEntries":23646,"totalTrips":214,"collectedTrips":377,"matchedTrips":127,"percentageMatched":0.5934579439252337},{"routeShortName":"3302A","totalEntries":24494,"totalTrips":122,"collectedTrips":214,"matchedTrips":105,"percentageMatched":0.860655737704918},{"routeShortName":"5104","totalEntries":12168,"totalTrips":109,"collectedTrips":151,"matchedTrips":85,"percentageMatched":0.7798165137614679},{"routeShortName":"838","totalEntries":1339,"totalTrips":40,"collectedTrips":29,"matchedTrips":16,"percentageMatched":0.4},{"routeShortName":"330","totalEntries":21097,"totalTrips":111,"collectedTrips":674,"matchedTrips":104,"percentageMatched":0.9369369369369369},{"routeShortName":"62","totalEntries":31703,"totalTrips":194,"collectedTrips":1014,"matchedTrips":132,"percentageMatched":0.6804123711340206},{"routeShortName":"8501","totalEntries":10747,"totalTrips":103,"collectedTrips":131,"matchedTrips":64,"percentageMatched":0.6213592233009708},{"routeShortName":"2150","totalEntries":3990,"totalTrips":61,"collectedTrips":76,"matchedTrips":42,"percentageMatched":0.6885245901639344},{"routeShortName":"311","totalEntries":7416,"totalTrips":78,"collectedTrips":95,"matchedTrips":59,"percentageMatched":0.7564102564102564},{"routeShortName":"8401","totalEntries":9484,"totalTrips":48,"collectedTrips":74,"matchedTrips":40,"percentageMatched":0.8333333333333334},{"routeShortName":"511","totalEntries":1551,"totalTrips":35,"collectedTrips":39,"matchedTrips":28,"percentageMatched":0.8},{"routeShortName":"9503","totalEntries":7111,"totalTrips":94,"collectedTrips":131,"matchedTrips":46,"percentageMatched":0.48936170212765956},{"routeShortName":"3055","totalEntries":14174,"totalTrips":83,"collectedTrips":123,"matchedTrips":68,"percentageMatched":0.8192771084337349},{"routeShortName":"4403D","totalEntries":9938,"totalTrips":49,"collectedTrips":77,"matchedTrips":47,"percentageMatched":0.9591836734693877},{"routeShortName":"8102","totalEntries":1220,"totalTrips":47,"collectedTrips":63,"matchedTrips":9,"percentageMatched":0.19148936170212766},{"routeShortName":"631","totalEntries":649,"totalTrips":9,"collectedTrips":11,"matchedTrips":9,"percentageMatched":1.0},{"routeShortName":"9208","totalEntries":9724,"totalTrips":105,"collectedTrips":181,"matchedTrips":68,"percentageMatched":0.6476190476190476},{"routeShortName":"4110","totalEntries":22387,"totalTrips":209,"collectedTrips":334,"matchedTrips":119,"percentageMatched":0.569377990430622},{"routeShortName":"9101","totalEntries":25463,"totalTrips":140,"collectedTrips":252,"matchedTrips":112,"percentageMatched":0.8},{"routeShortName":"814","totalEntries":5631,"totalTrips":71,"collectedTrips":79,"matchedTrips":54,"percentageMatched":0.7605633802816901},{"routeShortName":"9410","totalEntries":7295,"totalTrips":96,"collectedTrips":126,"matchedTrips":61,"percentageMatched":0.6354166666666666},{"routeShortName":"329","totalEntries":4160,"totalTrips":47,"collectedTrips":57,"matchedTrips":34,"percentageMatched":0.723404255319149},{"routeShortName":"332","totalEntries":6038,"totalTrips":50,"collectedTrips":60,"matchedTrips":35,"percentageMatched":0.7},{"routeShortName":"4501","totalEntries":9266,"totalTrips":100,"collectedTrips":139,"matchedTrips":56,"percentageMatched":0.56},{"routeShortName":"2103","totalEntries":10076,"totalTrips":124,"collectedTrips":154,"matchedTrips":90,"percentageMatched":0.7258064516129032},{"routeShortName":"301","totalEntries":553,"totalTrips":32,"collectedTrips":16,"matchedTrips":12,"percentageMatched":0.375},{"routeShortName":"713","totalEntries":5217,"totalTrips":63,"collectedTrips":84,"matchedTrips":59,"percentageMatched":0.9365079365079365},{"routeShortName":"641","totalEntries":6366,"totalTrips":68,"collectedTrips":91,"matchedTrips":66,"percentageMatched":0.9705882352941176},{"routeShortName":"4405","totalEntries":13735,"totalTrips":72,"collectedTrips":119,"matchedTrips":58,"percentageMatched":0.8055555555555556},{"routeShortName":"50","totalEntries":29755,"totalTrips":247,"collectedTrips":674,"matchedTrips":237,"percentageMatched":0.9595141700404858},{"routeShortName":"313","totalEntries":1696,"totalTrips":44,"collectedTrips":52,"matchedTrips":29,"percentageMatched":0.6590909090909091},{"routeShortName":"8405","totalEntries":8933,"totalTrips":89,"collectedTrips":116,"matchedTrips":65,"percentageMatched":0.7303370786516854},{"routeShortName":"622","totalEntries":1134,"totalTrips":19,"collectedTrips":28,"matchedTrips":16,"percentageMatched":0.8421052631578947},{"routeShortName":"5503A","totalEntries":11787,"totalTrips":78,"collectedTrips":126,"matchedTrips":63,"percentageMatched":0.8076923076923077},{"routeShortName":"6030","totalEntries":1379,"totalTrips":12,"collectedTrips":26,"matchedTrips":11,"percentageMatched":0.9166666666666666},{"routeShortName":"9407","totalEntries":13861,"totalTrips":141,"collectedTrips":217,"matchedTrips":101,"percentageMatched":0.7163120567375887},{"routeShortName":"61","totalEntries":15702,"totalTrips":117,"collectedTrips":1355,"matchedTrips":108,"percentageMatched":0.9230769230769231},{"routeShortName":"318","totalEntries":6826,"totalTrips":60,"collectedTrips":70,"matchedTrips":45,"percentageMatched":0.75},{"routeShortName":"9202","totalEntries":23461,"totalTrips":91,"collectedTrips":146,"matchedTrips":83,"percentageMatched":0.9120879120879121},{"routeShortName":"3050","totalEntries":32358,"totalTrips":216,"collectedTrips":331,"matchedTrips":150,"percentageMatched":0.6944444444444444},{"routeShortName":"4801A","totalEntries":9898,"totalTrips":90,"collectedTrips":124,"matchedTrips":58,"percentageMatched":0.6444444444444445},{"routeShortName":"618","totalEntries":15961,"totalTrips":161,"collectedTrips":246,"matchedTrips":134,"percentageMatched":0.8322981366459627},{"routeShortName":"204","totalEntries":1547,"totalTrips":31,"collectedTrips":35,"matchedTrips":23,"percentageMatched":0.7419354838709677},{"routeShortName":"8001A","totalEntries":13608,"totalTrips":145,"collectedTrips":227,"matchedTrips":93,"percentageMatched":0.6413793103448275},{"routeShortName":"620","totalEntries":4638,"totalTrips":52,"collectedTrips":63,"matchedTrips":49,"percentageMatched":0.9423076923076923},{"routeShortName":"616","totalEntries":12272,"totalTrips":107,"collectedTrips":146,"matchedTrips":92,"percentageMatched":0.8598130841121495},{"routeShortName":"3350","totalEntries":3333,"totalTrips":47,"collectedTrips":48,"matchedTrips":31,"percentageMatched":0.6595744680851063},{"routeShortName":"821","totalEntries":2036,"totalTrips":32,"collectedTrips":40,"matchedTrips":27,"percentageMatched":0.84375},{"routeShortName":"4034","totalEntries":11946,"totalTrips":54,"collectedTrips":84,"matchedTrips":45,"percentageMatched":0.8333333333333334},{"routeShortName":"4113","totalEntries":10194,"totalTrips":112,"collectedTrips":164,"matchedTrips":80,"percentageMatched":0.7142857142857143},{"routeShortName":"SC04A","totalEntries":5520,"totalTrips":59,"collectedTrips":76,"matchedTrips":54,"percentageMatched":0.9152542372881356},{"routeShortName":"621","totalEntries":5611,"totalTrips":68,"collectedTrips":77,"matchedTrips":65,"percentageMatched":0.9558823529411765},{"routeShortName":"9030","totalEntries":6135,"totalTrips":44,"collectedTrips":70,"matchedTrips":30,"percentageMatched":0.6818181818181818},{"routeShortName":"8551","totalEntries":3747,"totalTrips":42,"collectedTrips":59,"matchedTrips":38,"percentageMatched":0.9047619047619048},{"routeShortName":"645","totalEntries":5667,"totalTrips":59,"collectedTrips":70,"matchedTrips":56,"percentageMatched":0.9491525423728814},{"routeShortName":"337","totalEntries":3507,"totalTrips":45,"collectedTrips":53,"matchedTrips":35,"percentageMatched":0.7777777777777778},{"routeShortName":"9403","totalEntries":8316,"totalTrips":91,"collectedTrips":125,"matchedTrips":65,"percentageMatched":0.7142857142857143},{"routeShortName":"SC04B","totalEntries":4685,"totalTrips":55,"collectedTrips":63,"matchedTrips":42,"percentageMatched":0.7636363636363637},{"routeShortName":"4103","totalEntries":14417,"totalTrips":142,"collectedTrips":202,"matchedTrips":92,"percentageMatched":0.647887323943662},{"routeShortName":"901","totalEntries":7904,"totalTrips":56,"collectedTrips":79,"matchedTrips":31,"percentageMatched":0.5535714285714286},{"routeShortName":"82","totalEntries":21435,"totalTrips":146,"collectedTrips":1272,"matchedTrips":137,"percentageMatched":0.9383561643835616},{"routeShortName":"331","totalEntries":3685,"totalTrips":51,"collectedTrips":59,"matchedTrips":49,"percentageMatched":0.9607843137254902},{"routeShortName":"3502","totalEntries":8283,"totalTrips":82,"collectedTrips":115,"matchedTrips":59,"percentageMatched":0.7195121951219512},{"routeShortName":"3054","totalEntries":18705,"totalTrips":96,"collectedTrips":147,"matchedTrips":76,"percentageMatched":0.7916666666666666},{"routeShortName":"705","totalEntries":2007,"totalTrips":48,"collectedTrips":52,"matchedTrips":24,"percentageMatched":0.5},{"routeShortName":"1404A","totalEntries":10442,"totalTrips":109,"collectedTrips":149,"matchedTrips":51,"percentageMatched":0.46788990825688076},{"routeShortName":"5401","totalEntries":9468,"totalTrips":98,"collectedTrips":137,"matchedTrips":62,"percentageMatched":0.6326530612244898},{"routeShortName":"327","totalEntries":4462,"totalTrips":52,"collectedTrips":66,"matchedTrips":51,"percentageMatched":0.9807692307692307},{"routeShortName":"9414","totalEntries":13371,"totalTrips":109,"collectedTrips":144,"matchedTrips":88,"percentageMatched":0.8073394495412844},{"routeShortName":"406","totalEntries":2511,"totalTrips":38,"collectedTrips":34,"matchedTrips":28,"percentageMatched":0.7368421052631579},{"routeShortName":"9034","totalEntries":5377,"totalTrips":45,"collectedTrips":59,"matchedTrips":37,"percentageMatched":0.8222222222222222},{"routeShortName":"3503A","totalEntries":24779,"totalTrips":209,"collectedTrips":333,"matchedTrips":141,"percentageMatched":0.6746411483253588},{"routeShortName":"709","totalEntries":0,"totalTrips":0,"collectedTrips":0,"matchedTrips":0,"percentageMatched":"NaN"},{"routeShortName":"5106","totalEntries":11824,"totalTrips":134,"collectedTrips":185,"matchedTrips":80,"percentageMatched":0.5970149253731343},{"routeShortName":"642","totalEntries":5144,"totalTrips":58,"collectedTrips":67,"matchedTrips":50,"percentageMatched":0.8620689655172413},{"routeShortName":"1505","totalEntries":19008,"totalTrips":159,"collectedTrips":361,"matchedTrips":118,"percentageMatched":0.7421383647798742},{"routeShortName":"8108","totalEntries":6898,"totalTrips":44,"collectedTrips":59,"matchedTrips":38,"percentageMatched":0.8636363636363636},{"routeShortName":"813","totalEntries":5653,"totalTrips":69,"collectedTrips":88,"matchedTrips":52,"percentageMatched":0.7536231884057971},{"routeShortName":"314","totalEntries":4086,"totalTrips":45,"collectedTrips":55,"matchedTrips":31,"percentageMatched":0.6888888888888889},{"routeShortName":"714","totalEntries":3908,"totalTrips":46,"collectedTrips":55,"matchedTrips":44,"percentageMatched":0.9565217391304348},{"routeShortName":"5203","totalEntries":10289,"totalTrips":92,"collectedTrips":157,"matchedTrips":45,"percentageMatched":0.4891304347826087},{"routeShortName":"1030","totalEntries":2244,"totalTrips":22,"collectedTrips":39,"matchedTrips":20,"percentageMatched":0.9090909090909091},{"routeShortName":"8151","totalEntries":12744,"totalTrips":70,"collectedTrips":121,"matchedTrips":52,"percentageMatched":0.7428571428571429},{"routeShortName":"9404","totalEntries":2469,"totalTrips":84,"collectedTrips":110,"matchedTrips":24,"percentageMatched":0.2857142857142857},{"routeShortName":"707","totalEntries":6286,"totalTrips":75,"collectedTrips":96,"matchedTrips":66,"percentageMatched":0.88},{"routeShortName":"9214","totalEntries":7555,"totalTrips":95,"collectedTrips":130,"matchedTrips":51,"percentageMatched":0.5368421052631579},{"routeShortName":"32","totalEntries":10800,"totalTrips":75,"collectedTrips":564,"matchedTrips":51,"percentageMatched":0.68},{"routeShortName":"9103","totalEntries":7882,"totalTrips":62,"collectedTrips":82,"matchedTrips":50,"percentageMatched":0.8064516129032258},{"routeShortName":"310","totalEntries":4877,"totalTrips":48,"collectedTrips":57,"matchedTrips":42,"percentageMatched":0.875},{"routeShortName":"4031","totalEntries":10182,"totalTrips":49,"collectedTrips":83,"matchedTrips":34,"percentageMatched":0.6938775510204082},{"routeShortName":"206","totalEntries":5338,"totalTrips":41,"collectedTrips":57,"matchedTrips":37,"percentageMatched":0.9024390243902439},{"routeShortName":"902","totalEntries":1268,"totalTrips":26,"collectedTrips":29,"matchedTrips":20,"percentageMatched":0.7692307692307693},{"routeShortName":"3302B","totalEntries":12256,"totalTrips":54,"collectedTrips":104,"matchedTrips":44,"percentageMatched":0.8148148148148148},{"routeShortName":"SC01B","totalEntries":10312,"totalTrips":71,"collectedTrips":97,"matchedTrips":71,"percentageMatched":1.0},{"routeShortName":"335","totalEntries":4065,"totalTrips":47,"collectedTrips":102,"matchedTrips":34,"percentageMatched":0.723404255319149},{"routeShortName":"9210","totalEntries":4020,"totalTrips":89,"collectedTrips":111,"matchedTrips":42,"percentageMatched":0.47191011235955055},{"routeShortName":"9032","totalEntries":6515,"totalTrips":58,"collectedTrips":107,"matchedTrips":42,"percentageMatched":0.7241379310344828},{"routeShortName":"8103","totalEntries":10145,"totalTrips":136,"collectedTrips":196,"matchedTrips":86,"percentageMatched":0.6323529411764706},{"routeShortName":"9405","totalEntries":6240,"totalTrips":88,"collectedTrips":106,"matchedTrips":60,"percentageMatched":0.6818181818181818},{"routeShortName":"9204","totalEntries":8660,"totalTrips":95,"collectedTrips":134,"matchedTrips":58,"percentageMatched":0.6105263157894737},{"routeShortName":"736","totalEntries":3095,"totalTrips":54,"collectedTrips":65,"matchedTrips":47,"percentageMatched":0.8703703703703703},{"routeShortName":"9105","totalEntries":6434,"totalTrips":87,"collectedTrips":108,"matchedTrips":49,"percentageMatched":0.5632183908045977},{"routeShortName":"66","totalEntries":18745,"totalTrips":99,"collectedTrips":174,"matchedTrips":88,"percentageMatched":0.8888888888888888},{"routeShortName":"3030","totalEntries":11828,"totalTrips":75,"collectedTrips":101,"matchedTrips":55,"percentageMatched":0.7333333333333333},{"routeShortName":"737","totalEntries":8137,"totalTrips":80,"collectedTrips":125,"matchedTrips":74,"percentageMatched":0.925},{"routeShortName":"5102","totalEntries":8407,"totalTrips":50,"collectedTrips":71,"matchedTrips":40,"percentageMatched":0.8},{"routeShortName":"806","totalEntries":6180,"totalTrips":71,"collectedTrips":97,"matchedTrips":48,"percentageMatched":0.676056338028169},{"routeShortName":"63","totalEntries":11824,"totalTrips":75,"collectedTrips":929,"matchedTrips":73,"percentageMatched":0.9733333333333334},{"routeShortName":"9412","totalEntries":12890,"totalTrips":128,"collectedTrips":205,"matchedTrips":85,"percentageMatched":0.6640625},{"routeShortName":"9209","totalEntries":3242,"totalTrips":76,"collectedTrips":93,"matchedTrips":35,"percentageMatched":0.4605263157894737},{"routeShortName":"201","totalEntries":1308,"totalTrips":28,"collectedTrips":32,"matchedTrips":15,"percentageMatched":0.5357142857142857},{"routeShortName":"4201","totalEntries":9165,"totalTrips":108,"collectedTrips":135,"matchedTrips":71,"percentageMatched":0.6574074074074074},{"routeShortName":"3301B","totalEntries":8021,"totalTrips":45,"collectedTrips":71,"matchedTrips":38,"percentageMatched":0.8444444444444444},{"routeShortName":"825","totalEntries":3726,"totalTrips":59,"collectedTrips":75,"matchedTrips":32,"percentageMatched":0.5423728813559322},{"routeShortName":"639","totalEntries":0,"totalTrips":0,"collectedTrips":0,"matchedTrips":0,"percentageMatched":"NaN"},{"routeShortName":"3052","totalEntries":11728,"totalTrips":76,"collectedTrips":124,"matchedTrips":61,"percentageMatched":0.8026315789473685},{"routeShortName":"626","totalEntries":11069,"totalTrips":114,"collectedTrips":156,"matchedTrips":93,"percentageMatched":0.8157894736842105},{"routeShortName":"609","totalEntries":9713,"totalTrips":51,"collectedTrips":75,"matchedTrips":47,"percentageMatched":0.9215686274509803},{"routeShortName":"9805","totalEntries":5954,"totalTrips":95,"collectedTrips":124,"matchedTrips":51,"percentageMatched":0.5368421052631579},{"routeShortName":"35","totalEntries":11223,"totalTrips":65,"collectedTrips":799,"matchedTrips":61,"percentageMatched":0.9384615384615385},{"routeShortName":"4033","totalEntries":8256,"totalTrips":45,"collectedTrips":72,"matchedTrips":37,"percentageMatched":0.8222222222222222},{"routeShortName":"812","totalEntries":0,"totalTrips":0,"collectedTrips":0,"matchedTrips":0,"percentageMatched":"NaN"},{"routeShortName":"1404C","totalEntries":10890,"totalTrips":95,"collectedTrips":145,"matchedTrips":58,"percentageMatched":0.6105263157894737},{"routeShortName":"739","totalEntries":5908,"totalTrips":55,"collectedTrips":69,"matchedTrips":51,"percentageMatched":0.9272727272727272},{"routeShortName":"325","totalEntries":6993,"totalTrips":59,"collectedTrips":171,"matchedTrips":57,"percentageMatched":0.9661016949152542},{"routeShortName":"9402","totalEntries":7200,"totalTrips":87,"collectedTrips":116,"matchedTrips":64,"percentageMatched":0.735632183908046},{"routeShortName":"4102","totalEntries":10783,"totalTrips":116,"collectedTrips":141,"matchedTrips":94,"percentageMatched":0.8103448275862069},{"routeShortName":"706","totalEntries":1467,"totalTrips":46,"collectedTrips":56,"matchedTrips":19,"percentageMatched":0.41304347826086957},{"routeShortName":"9801","totalEntries":10665,"totalTrips":94,"collectedTrips":133,"matchedTrips":77,"percentageMatched":0.8191489361702128},{"routeShortName":"807","totalEntries":3248,"totalTrips":52,"collectedTrips":61,"matchedTrips":25,"percentageMatched":0.4807692307692308},{"routeShortName":"67","totalEntries":16201,"totalTrips":107,"collectedTrips":191,"matchedTrips":75,"percentageMatched":0.7009345794392523},{"routeShortName":"SC01R","totalEntries":4502,"totalTrips":37,"collectedTrips":63,"matchedTrips":35,"percentageMatched":0.9459459459459459},{"routeShortName":"732","totalEntries":0,"totalTrips":0,"collectedTrips":0,"matchedTrips":0,"percentageMatched":"NaN"},{"routeShortName":"836","totalEntries":0,"totalTrips":0,"collectedTrips":0,"matchedTrips":0,"percentageMatched":"NaN"},{"routeShortName":"9415","totalEntries":6013,"totalTrips":44,"collectedTrips":63,"matchedTrips":31,"percentageMatched":0.7045454545454546},{"routeShortName":"51","totalEntries":25326,"totalTrips":207,"collectedTrips":1776,"matchedTrips":182,"percentageMatched":0.8792270531400966},{"routeShortName":"734","totalEntries":1514,"totalTrips":33,"collectedTrips":39,"matchedTrips":21,"percentageMatched":0.6363636363636364},{"routeShortName":"4107","totalEntries":5680,"totalTrips":95,"collectedTrips":90,"matchedTrips":49,"percentageMatched":0.5157894736842106},{"routeShortName":"503","totalEntries":9761,"totalTrips":52,"collectedTrips":208,"matchedTrips":47,"percentageMatched":0.9038461538461539},{"routeShortName":"303","totalEntries":5579,"totalTrips":46,"collectedTrips":157,"matchedTrips":42,"percentageMatched":0.9130434782608695},{"routeShortName":"504","totalEntries":5190,"totalTrips":50,"collectedTrips":78,"matchedTrips":33,"percentageMatched":0.66},{"routeShortName":"832","totalEntries":6224,"totalTrips":75,"collectedTrips":101,"matchedTrips":51,"percentageMatched":0.68},{"routeShortName":"5506A","totalEntries":11149,"totalTrips":59,"collectedTrips":90,"matchedTrips":51,"percentageMatched":0.864406779661017},{"routeShortName":"533","totalEntries":0,"totalTrips":0,"collectedTrips":0,"matchedTrips":0,"percentageMatched":"NaN"},{"routeShortName":"336","totalEntries":1057,"totalTrips":26,"collectedTrips":30,"matchedTrips":26,"percentageMatched":1.0},{"routeShortName":"340","totalEntries":5698,"totalTrips":46,"collectedTrips":55,"matchedTrips":37,"percentageMatched":0.8043478260869565},{"routeShortName":"837","totalEntries":4868,"totalTrips":50,"collectedTrips":70,"matchedTrips":46,"percentageMatched":0.92},{"routeShortName":"3250","totalEntries":10081,"totalTrips":71,"collectedTrips":107,"matchedTrips":64,"percentageMatched":0.9014084507042254},{"routeShortName":"640","totalEntries":4739,"totalTrips":49,"collectedTrips":60,"matchedTrips":46,"percentageMatched":0.9387755102040817},{"routeShortName":"107","totalEntries":1763,"totalTrips":28,"collectedTrips":21,"matchedTrips":15,"percentageMatched":0.5357142857142857},{"routeShortName":"52","totalEntries":12059,"totalTrips":72,"collectedTrips":1009,"matchedTrips":71,"percentageMatched":0.9861111111111112},{"routeShortName":"607","totalEntries":16911,"totalTrips":144,"collectedTrips":222,"matchedTrips":127,"percentageMatched":0.8819444444444444},{"routeShortName":"5503B","totalEntries":5802,"totalTrips":46,"collectedTrips":77,"matchedTrips":31,"percentageMatched":0.6739130434782609},{"routeShortName":"83D","totalEntries":17264,"totalTrips":227,"collectedTrips":326,"matchedTrips":197,"percentageMatched":0.8678414096916299},{"routeShortName":"30","totalEntries":52748,"totalTrips":289,"collectedTrips":2073,"matchedTrips":230,"percentageMatched":0.7958477508650519},{"routeShortName":"308","totalEntries":3945,"totalTrips":52,"collectedTrips":70,"matchedTrips":44,"percentageMatched":0.8461538461538461},{"routeShortName":"321","totalEntries":1301,"totalTrips":31,"collectedTrips":37,"matchedTrips":20,"percentageMatched":0.6451612903225806},{"routeShortName":"617","totalEntries":18087,"totalTrips":193,"collectedTrips":317,"matchedTrips":152,"percentageMatched":0.7875647668393783},{"routeShortName":"302","totalEntries":10509,"totalTrips":91,"collectedTrips":205,"matchedTrips":84,"percentageMatched":0.9230769230769231},{"routeShortName":"83P","totalEntries":7285,"totalTrips":76,"collectedTrips":97,"matchedTrips":73,"percentageMatched":0.9605263157894737},{"routeShortName":"811","totalEntries":2241,"totalTrips":49,"collectedTrips":61,"matchedTrips":19,"percentageMatched":0.3877551020408163},{"routeShortName":"65","totalEntries":14517,"totalTrips":122,"collectedTrips":173,"matchedTrips":116,"percentageMatched":0.9508196721311475},{"routeShortName":"912","totalEntries":0,"totalTrips":30,"collectedTrips":0,"matchedTrips":0,"percentageMatched":0.0},{"routeShortName":"208","totalEntries":6097,"totalTrips":48,"collectedTrips":65,"matchedTrips":42,"percentageMatched":0.875},{"routeShortName":"4802A","totalEntries":15380,"totalTrips":170,"collectedTrips":241,"matchedTrips":94,"percentageMatched":0.5529411764705883},{"routeShortName":"2101","totalEntries":16015,"totalTrips":208,"collectedTrips":282,"matchedTrips":132,"percentageMatched":0.6346153846153846},{"routeShortName":"8550","totalEntries":0,"totalTrips":0,"collectedTrips":0,"matchedTrips":0,"percentageMatched":"NaN"},{"routeShortName":"2152","totalEntries":4629,"totalTrips":60,"collectedTrips":81,"matchedTrips":45,"percentageMatched":0.75},{"routeShortName":"3301A","totalEntries":8902,"totalTrips":41,"collectedTrips":65,"matchedTrips":29,"percentageMatched":0.7073170731707317},{"routeShortName":"102","totalEntries":5596,"totalTrips":52,"collectedTrips":61,"matchedTrips":45,"percentageMatched":0.8653846153846154},{"routeShortName":"710","totalEntries":0,"totalTrips":0,"collectedTrips":0,"matchedTrips":0,"percentageMatched":"NaN"},{"routeShortName":"703","totalEntries":3719,"totalTrips":45,"collectedTrips":62,"matchedTrips":42,"percentageMatched":0.9333333333333333},{"routeShortName":"535","totalEntries":0,"totalTrips":0,"collectedTrips":0,"matchedTrips":0,"percentageMatched":"NaN"},{"routeShortName":"6350","totalEntries":17432,"totalTrips":195,"collectedTrips":311,"matchedTrips":114,"percentageMatched":0.5846153846153846},{"routeShortName":"104","totalEntries":8476,"totalTrips":95,"collectedTrips":114,"matchedTrips":86,"percentageMatched":0.9052631578947369},{"routeShortName":"304","totalEntries":1484,"totalTrips":46,"collectedTrips":54,"matchedTrips":17,"percentageMatched":0.3695652173913043},{"routeShortName":"9411","totalEntries":6747,"totalTrips":96,"collectedTrips":132,"matchedTrips":47,"percentageMatched":0.4895833333333333},{"routeShortName":"1170","totalEntries":3938,"totalTrips":62,"collectedTrips":78,"matchedTrips":50,"percentageMatched":0.8064516129032258},{"routeShortName":"8208","totalEntries":11613,"totalTrips":98,"collectedTrips":140,"matchedTrips":75,"percentageMatched":0.7653061224489796},{"routeShortName":"740","totalEntries":744,"totalTrips":28,"collectedTrips":19,"matchedTrips":12,"percentageMatched":0.42857142857142855},{"routeShortName":"6031","totalEntries":1108,"totalTrips":12,"collectedTrips":18,"matchedTrips":12,"percentageMatched":1.0},{"routeShortName":"708","totalEntries":3341,"totalTrips":46,"collectedTrips":58,"matchedTrips":30,"percentageMatched":0.6521739130434783},{"routeShortName":"809","totalEntries":4656,"totalTrips":52,"collectedTrips":67,"matchedTrips":37,"percentageMatched":0.7115384615384616},{"routeShortName":"826","totalEntries":1067,"totalTrips":27,"collectedTrips":30,"matchedTrips":27,"percentageMatched":1.0},{"routeShortName":"2033","totalEntries":355,"totalTrips":2,"collectedTrips":6,"matchedTrips":2,"percentageMatched":1.0},{"routeShortName":"8150","totalEntries":5111,"totalTrips":88,"collectedTrips":108,"matchedTrips":51,"percentageMatched":0.5795454545454546},{"routeShortName":"810","totalEntries":6556,"totalTrips":50,"collectedTrips":828,"matchedTrips":49,"percentageMatched":0.98},{"routeShortName":"4150","totalEntries":8523,"totalTrips":92,"collectedTrips":128,"matchedTrips":57,"percentageMatched":0.6195652173913043},{"routeShortName":"624","totalEntries":4937,"totalTrips":66,"collectedTrips":80,"matchedTrips":65,"percentageMatched":0.9848484848484849},{"routeShortName":"8207","totalEntries":18351,"totalTrips":162,"collectedTrips":324,"matchedTrips":111,"percentageMatched":0.6851851851851852},{"routeShortName":"3501B","totalEntries":11467,"totalTrips":97,"collectedTrips":129,"matchedTrips":77,"percentageMatched":0.7938144329896907},{"routeShortName":"4403C","totalEntries":5366,"totalTrips":29,"collectedTrips":44,"matchedTrips":29,"percentageMatched":1.0},{"routeShortName":"638","totalEntries":1043,"totalTrips":44,"collectedTrips":53,"matchedTrips":13,"percentageMatched":0.29545454545454547},{"routeShortName":"735","totalEntries":3346,"totalTrips":63,"collectedTrips":76,"matchedTrips":53,"percentageMatched":0.8412698412698413},{"routeShortName":"4106","totalEntries":3901,"totalTrips":41,"collectedTrips":54,"matchedTrips":25,"percentageMatched":0.6097560975609756},{"routeShortName":"1505R","totalEntries":10476,"totalTrips":61,"collectedTrips":93,"matchedTrips":56,"percentageMatched":0.9180327868852459},{"routeShortName":"636","totalEntries":5347,"totalTrips":57,"collectedTrips":81,"matchedTrips":54,"percentageMatched":0.9473684210526315},{"routeShortName":"8350","totalEntries":8619,"totalTrips":148,"collectedTrips":229,"matchedTrips":71,"percentageMatched":0.4797297297297297},{"routeShortName":"205","totalEntries":6325,"totalTrips":59,"collectedTrips":72,"matchedTrips":47,"percentageMatched":0.7966101694915254},{"routeShortName":"635","totalEntries":7823,"totalTrips":57,"collectedTrips":386,"matchedTrips":57,"percentageMatched":1.0},{"routeShortName":"1145","totalEntries":9028,"totalTrips":48,"collectedTrips":78,"matchedTrips":39,"percentageMatched":0.8125},{"routeShortName":"5550","totalEntries":5605,"totalTrips":126,"collectedTrips":153,"matchedTrips":65,"percentageMatched":0.5158730158730159},{"routeShortName":"1510","totalEntries":8523,"totalTrips":95,"collectedTrips":136,"matchedTrips":51,"percentageMatched":0.5368421052631579},{"routeShortName":"715","totalEntries":7534,"totalTrips":75,"collectedTrips":107,"matchedTrips":72,"percentageMatched":0.96},{"routeShortName":"101","totalEntries":5081,"totalTrips":46,"collectedTrips":59,"matchedTrips":41,"percentageMatched":0.8913043478260869},{"routeShortName":"2104","totalEntries":17837,"totalTrips":167,"collectedTrips":301,"matchedTrips":103,"percentageMatched":0.6167664670658682},{"routeShortName":"4410","totalEntries":8824,"totalTrips":45,"collectedTrips":71,"matchedTrips":42,"percentageMatched":0.9333333333333333},{"routeShortName":"822","totalEntries":4252,"totalTrips":34,"collectedTrips":50,"matchedTrips":30,"percentageMatched":0.8823529411764706},{"routeShortName":"2035","totalEntries":7193,"totalTrips":45,"collectedTrips":71,"matchedTrips":40,"percentageMatched":0.8888888888888888},{"routeShortName":"5033","totalEntries":15757,"totalTrips":73,"collectedTrips":136,"matchedTrips":67,"percentageMatched":0.9178082191780822},{"routeShortName":"9206","totalEntries":12005,"totalTrips":94,"collectedTrips":143,"matchedTrips":65,"percentageMatched":0.6914893617021277},{"routeShortName":"903","totalEntries":3359,"totalTrips":25,"collectedTrips":264,"matchedTrips":24,"percentageMatched":0.96},{"routeShortName":"623","totalEntries":3350,"totalTrips":50,"collectedTrips":56,"matchedTrips":43,"percentageMatched":0.86},{"routeShortName":"702","totalEntries":3797,"totalTrips":44,"collectedTrips":58,"matchedTrips":35,"percentageMatched":0.7954545454545454},{"routeShortName":"711","totalEntries":6374,"totalTrips":69,"collectedTrips":98,"matchedTrips":59,"percentageMatched":0.855072463768116},{"routeShortName":"720","totalEntries":0,"totalTrips":25,"collectedTrips":0,"matchedTrips":0,"percentageMatched":0.0}]}